<annotation>
    <folder>VOC2007</folder>
    <filename>annotation[bread]Bing_314.jpeg</filename>
    <source>
        <database>My Database</database>
        <annotation>VOC2007</annotation>
        <image>flickr</image>
        <flickrid>NULL</flickrid>
    </source>
    <owner>
        <flickrid>NULL</flickrid>
        <name>x</name>
    </owner>
    <size>
        <width>4320</width>
        <height>3240</height>
        <depth>3</depth>
    </size>
    <segmented>0</segmented>
    <object>
        <name>bread</name>
        <pose>Unspecified</pose>
        <truncated>0</truncated>
        <difficult>0</difficult>
        <bndbox>
            <xmin>105</xmin>
            <ymin>9</ymin>
            <xmax>3062</xmax>
            <ymax>3204</ymax>
        </bndbox>
    </object>
    <object>
        <name>bread</name>
        <pose>Unspecified</pose>
        <truncated>0</truncated>
        <difficult>0</difficult>
        <bndbox>
            <xmin>2826</xmin>
            <ymin>42</ymin>
            <xmax>4317</xmax>
            <ymax>2225</ymax>
        </bndbox>
    </object>
</annotation>