<annotation>
    <folder>VOC2007</folder>
    <filename>annotation[chilies]Bing_399.jpeg</filename>
    <source>
        <database>My Database</database>
        <annotation>VOC2007</annotation>
        <image>flickr</image>
        <flickrid>NULL</flickrid>
    </source>
    <owner>
        <flickrid>NULL</flickrid>
        <name>x</name>
    </owner>
    <size>
        <width>730</width>
        <height>1095</height>
        <depth>3</depth>
    </size>
    <segmented>0</segmented>
    <object>
        <name>chilies</name>
        <pose>Unspecified</pose>
        <truncated>0</truncated>
        <difficult>0</difficult>
        <bndbox>
            <xmin>151</xmin>
            <ymin>6</ymin>
            <xmax>724</xmax>
            <ymax>1084</ymax>
        </bndbox>
    </object>
</annotation>