<annotation>
    <folder>VOC2007</folder>
    <filename>annotation[fruit]Bing_481.jpeg</filename>
    <source>
        <database>My Database</database>
        <annotation>VOC2007</annotation>
        <image>flickr</image>
        <flickrid>NULL</flickrid>
    </source>
    <owner>
        <flickrid>NULL</flickrid>
        <name>x</name>
    </owner>
    <size>
        <width>360</width>
        <height>473</height>
        <depth>3</depth>
    </size>
    <segmented>0</segmented>
    <object>
        <name>fruit</name>
        <pose>Unspecified</pose>
        <truncated>0</truncated>
        <difficult>0</difficult>
        <bndbox>
            <xmin>90</xmin>
            <ymin>97</ymin>
            <xmax>220</xmax>
            <ymax>249</ymax>
        </bndbox>
    </object>
    <object>
        <name>fruit</name>
        <pose>Unspecified</pose>
        <truncated>0</truncated>
        <difficult>0</difficult>
        <bndbox>
            <xmin>125</xmin>
            <ymin>320</ymin>
            <xmax>238</xmax>
            <ymax>427</ymax>
        </bndbox>
    </object>
</annotation>