<annotation>
    <folder>VOC2007</folder>
    <filename>annotation[milk_after]Bing_303.jpeg</filename>
    <source>
        <database>My Database</database>
        <annotation>VOC2007</annotation>
        <image>flickr</image>
        <flickrid>NULL</flickrid>
    </source>
    <owner>
        <flickrid>NULL</flickrid>
        <name>x</name>
    </owner>
    <size>
        <width>406</width>
        <height>250</height>
        <depth>3</depth>
    </size>
    <segmented>0</segmented>
    <object>
        <name>milk_after</name>
        <pose>Unspecified</pose>
        <truncated>0</truncated>
        <difficult>0</difficult>
        <bndbox>
            <xmin>174</xmin>
            <ymin>33</ymin>
            <xmax>390</xmax>
            <ymax>249</ymax>
        </bndbox>
    </object>
    <object>
        <name>milk_after</name>
        <pose>Unspecified</pose>
        <truncated>0</truncated>
        <difficult>0</difficult>
        <bndbox>
            <xmin>0</xmin>
            <ymin>0</ymin>
            <xmax>279</xmax>
            <ymax>150</ymax>
        </bndbox>
    </object>
</annotation>